lab3/task1/lfsr.sv
module lfsr (
    input logic clk,
    input logic en,
    input logic rst,
    output logic [4:1] data_out
);

    logic [4:1] sreg;

always_ff @ (posedge clk, posedge rst)
    if (rst) sreg <= 4'b1;
    else if (en) sreg <= {sreg[3:1], sreg[4]^sreg[3]};

assign data_out = sreg;
endmodule

lab3/task1/lfsr.vcd
$version Generated by VerilatedVcd $end
$date Thu Oct 31 12:15:20 2024 $end
$timescale 1ps $end

 $scope module TOP $end
  $var wire  1 # clk $end
  $var wire  4 & data_out [4:1] $end
  $var wire  1 $ en $end
  $var wire  1 % rst $end
  $scope module lfsr $end
   $var wire  1 # clk $end
   $var wire  4 & data_out [4:1] $end
   $var wire  1 $ en $end
   $var wire  1 % rst $end
   $var wire  4 ' sreg [4:1] $end
  $upscope $end
 $upscope $end
$enddefinitions $end


#0
1#
1$
1%
b0000 &
b0000 '
#1
0#
#2
1#
b0001 &
b0001 '
#3
0#
#4
1#
#5
0#
#6
1#
0%
#7
0#
#8
1#
b0010 &
b0010 '
#9
0#
#10
1#
b0100 &
b0100 '
#11
0#
#12
1#
b1001 &
b1001 '
#13
0#
#14
1#
b0011 &
b0011 '
#15
0#
#16
1#
b0110 &
b0110 '
#17
0#
#18
1#
b1101 &
b1101 '
#19
0#
#20
1#
b1010 &
b1010 '
#21
0#
#22
1#
b0101 &
b0101 '
#23
0#
#24
1#
b1011 &
b1011 '
#25
0#
#26
1#
b0111 &
b0111 '
#27
0#
#28
1#
b1111 &
b1111 '
#29
0#
#30
1#
b1110 &
b1110 '
#31
0#
#32
1#
b1100 &
b1100 '
#33
0#
#34
1#
b1000 &
b1000 '
#35
0#
#36
1#
b0001 &
b0001 '
#37
0#
#38
1#
b0010 &
b0010 '
#39
0#
#40
1#
b0100 &
b0100 '
#41
0#
#42
1#
b1001 &
b1001 '
#43
0#
#44
1#
b0011 &
b0011 '
#45
0#
#46
1#
b0110 &
b0110 '
#47
0#
#48
1#
b1101 &
b1101 '
#49
0#
#50
1#
b1010 &
b1010 '
#51
0#
#52
1#
b0101 &
b0101 '
#53
0#
#54
1#
b1011 &
b1011 '
#55
0#
#56
1#
b0111 &
b0111 '
#57
0#
#58
1#
b1111 &
b1111 '
#59
0#
#60
1#
b1110 &
b1110 '
#61
0#
#62
1#
b1100 &
b1100 '
#63
0#
#64
1#
b1000 &
b1000 '
#65
0#
#66
1#
b0001 &
b0001 '
#67
0#
#68
1#
b0010 &
b0010 '
#69
0#
#70
1#
b0100 &
b0100 '
#71
0#
#72
1#
b1001 &
b1001 '
#73
0#
#74
1#
b0011 &
b0011 '
#75
0#
#76
1#
b0110 &
b0110 '
#77
0#
#78
1#
b1101 &
b1101 '
#79
0#
#80
1#
b1010 &
b1010 '
#81
0#
#82
1#
b0101 &
b0101 '
#83
0#
#84
1#
b1011 &
b1011 '
#85
0#
#86
1#
b0111 &
b0111 '
#87
0#
#88
1#
b1111 &
b1111 '
#89
0#
#90
1#
b1110 &
b1110 '
#91
0#
#92
1#
b1100 &
b1100 '
#93
0#
#94
1#
b1000 &
b1000 '
#95
0#
#96
1#
b0001 &
b0001 '
#97
0#
#98
1#
b0010 &
b0010 '
#99
0#
#100
1#
b0100 &
b0100 '
#101
0#
#102
1#
b1001 &
b1001 '
#103
0#
#104
1#
b0011 &
b0011 '
#105
0#
#106
1#
b0110 &
b0110 '
#107
0#
#108
1#
b1101 &
b1101 '
#109
0#
#110
1#
b1010 &
b1010 '
#111
0#
#112
1#
b0101 &
b0101 '
#113
0#
#114
1#
b1011 &
b1011 '
#115
0#
#116
1#
b0111 &
b0111 '
#117
0#
#118
1#
b1111 &
b1111 '
#119
0#
#120
1#
b1110 &
b1110 '
#121
0#
#122
1#
b1100 &
b1100 '
#123
0#
#124
1#
b1000 &
b1000 '
#125
0#
#126
1#
b0001 &
b0001 '
#127
0#
#128
1#
b0010 &
b0010 '
#129
0#
#130
1#
b0100 &
b0100 '
#131
0#
#132
1#
b1001 &
b1001 '
#133
0#
#134
1#
b0011 &
b0011 '
#135
0#
#136
1#
b0110 &
b0110 '
#137
0#
#138
1#
b1101 &
b1101 '
#139
0#
#140
1#
b1010 &
b1010 '
#141
0#
#142
1#
b0101 &
b0101 '
#143
0#
#144
1#
b1011 &
b1011 '
#145
0#
#146
1#
b0111 &
b0111 '
#147
0#
#148
1#
b1111 &
b1111 '
#149
0#
#150
1#
b1110 &
b1110 '
#151
0#
#152
1#
b1100 &
b1100 '
#153
0#
#154
1#
b1000 &
b1000 '
#155
0#
#156
1#
b0001 &
b0001 '
#157
0#
#158
1#
b0010 &
b0010 '
#159
0#
#160
1#
b0100 &
b0100 '
#161
0#
#162
1#
b1001 &
b1001 '
#163
0#
#164
1#
b0011 &
b0011 '
#165
0#
#166
1#
b0110 &
b0110 '
#167
0#
#168
1#
b1101 &
b1101 '
#169
0#
#170
1#
b1010 &
b1010 '
#171
0#
#172
1#
b0101 &
b0101 '
#173
0#
#174
1#
b1011 &
b1011 '
#175
0#
#176
1#
b0111 &
b0111 '
#177
0#
#178
1#
b1111 &
b1111 '
#179
0#
#180
1#
b1110 &
b1110 '
#181
0#
#182
1#
b1100 &
b1100 '
#183
0#
#184
1#
b1000 &
b1000 '
#185
0#
#186
1#
b0001 &
b0001 '
#187
0#
#188
1#
b0010 &
b0010 '
#189
0#
#190
1#
b0100 &
b0100 '
#191
0#
#192
1#
b1001 &
b1001 '
#193
0#
#194
1#
b0011 &
b0011 '
#195
0#
#196
1#
b0110 &
b0110 '
#197
0#
#198
1#
b1101 &
b1101 '
#199
0#
#200
1#
b1010 &
b1010 '
#201
0#
#202
1#
b0101 &
b0101 '
#203
0#
#204
1#
b1011 &
b1011 '
#205
0#
#206
1#
b0111 &
b0111 '
#207
0#
#208
1#
b1111 &
b1111 '
#209
0#
#210
1#
b1110 &
b1110 '
#211
0#
#212
1#
b1100 &
b1100 '
#213
0#
#214
1#
b1000 &
b1000 '
#215
0#
#216
1#
b0001 &
b0001 '
#217
0#
#218
1#
b0010 &
b0010 '
#219
0#
#220
1#
b0100 &
b0100 '
#221
0#
#222
1#
b1001 &
b1001 '
#223
0#
#224
1#
b0011 &
b0011 '
#225
0#
#226
1#
b0110 &
b0110 '
#227
0#
#228
1#
b1101 &
b1101 '
#229
0#
#230
1#
b1010 &
b1010 '
#231
0#
#232
1#
b0101 &
b0101 '
#233
0#
#234
1#
b1011 &
b1011 '
#235
0#
#236
1#
b0111 &
b0111 '
#237
0#
#238
1#
b1111 &
b1111 '
#239
0#
#240
1#
b1110 &
b1110 '
#241
0#
#242
1#
b1100 &
b1100 '
#243
0#
#244
1#
b1000 &
b1000 '
#245
0#
#246
1#
b0001 &
b0001 '
#247
0#
#248
1#
b0010 &
b0010 '
#249
0#
#250
1#
b0100 &
b0100 '
#251
0#
#252
1#
b1001 &
b1001 '
#253
0#
#254
1#
b0011 &
b0011 '
#255
0#
#256
1#
b0110 &
b0110 '
#257
0#
#258
1#
b1101 &
b1101 '
#259
0#
#260
1#
b1010 &
b1010 '
#261
0#
#262
1#
b0101 &
b0101 '
#263
0#
#264
1#
b1011 &
b1011 '
#265
0#
#266
1#
b0111 &
b0111 '
#267
0#
#268
1#
b1111 &
b1111 '
#269
0#
#270
1#
b1110 &
b1110 '
#271
0#
#272
1#
b1100 &
b1100 '
#273
0#
#274
1#
b1000 &
b1000 '
#275
0#
#276
1#
b0001 &
b0001 '
#277
0#
#278
1#
b0010 &
b0010 '
#279
0#
#280
1#
b0100 &
b0100 '
#281
0#
#282
1#
b1001 &
b1001 '
#283
0#
#284
1#
b0011 &
b0011 '
#285
0#
#286
1#
b0110 &
b0110 '
#287
0#
#288
1#
b1101 &
b1101 '
#289
0#
#290
1#
b1010 &
b1010 '
#291
0#
#292
1#
b0101 &
b0101 '
#293
0#
#294
1#
b1011 &
b1011 '
#295
0#
#296
1#
b0111 &
b0111 '
#297
0#
#298
1#
b1111 &
b1111 '
#299
0#
#300
1#
b1110 &
b1110 '
#301
0#
#302
1#
b1100 &
b1100 '
#303
0#
#304
1#
b1000 &
b1000 '
#305
0#
#306
1#
b0001 &
b0001 '
#307
0#
#308
1#
b0010 &
b0010 '
#309
0#
#310
1#
b0100 &
b0100 '
#311
0#
#312
1#
b1001 &
b1001 '
#313
0#
#314
1#
b0011 &
b0011 '
#315
0#
#316
1#
b0110 &
b0110 '
#317
0#
#318
1#
b1101 &
b1101 '
#319
0#
#320
1#
b1010 &
b1010 '
#321
0#
#322
1#
b0101 &
b0101 '
#323
0#
#324
1#
b1011 &
b1011 '
#325
0#
#326
1#
b0111 &
b0111 '
#327
0#
#328
1#
b1111 &
b1111 '
#329
0#
#330
1#
b1110 &
b1110 '
#331
0#
#332
1#
b1100 &
b1100 '
#333
0#
#334
1#
b1000 &
b1000 '
#335
0#
#336
1#
b0001 &
b0001 '
#337
0#
#338
1#
b0010 &
b0010 '
#339
0#
#340
1#
b0100 &
b0100 '
#341
0#
#342
1#
b1001 &
b1001 '
#343
0#
#344
1#
b0011 &
b0011 '
#345
0#
#346
1#
b0110 &
b0110 '
#347
0#
#348
1#
b1101 &
b1101 '
#349
0#
#350
1#
b1010 &
b1010 '
#351
0#
#352
1#
0$
b0101 &
b0101 '
