lab2/task3/ram.sv
module ram #(
    parameter ADDRESS_WIDTH = 9,
              DATA_WIDTH = 8
)(
    input logic clk,
    input logic readEn,
    input logic writeEn,
    input logic [ADDRESS_WIDTH-1:0] writeAddr,
    input logic [ADDRESS_WIDTH-1:0] readAddr,
    input logic [DATA_WIDTH-1:0] din,
    output logic [DATA_WIDTH-1:0] dout
);

logic [DATA_WIDTH-1:0] ram_array [2**ADDRESS_WIDTH-1:0];

always_ff @(posedge clk) begin
    if (writeEn == 1'b1)
        ram_array[writeAddr] <= din;
    if (readEn == 1'b1)
        dout <= ram_array[readAddr];
    end

endmodule

lab2/task3/counter.sv
module counter #(
  parameter WIDTH = 8
)(
  // interface signals
  input  logic             clk,      // clock
  input  logic             rst,      // reset
  output logic [WIDTH-1:0] count     // count output
);

always_ff @ (posedge clk)
  if (rst) count <= {WIDTH{1'b0}};
  else count <= count + 1'b1;
endmodule

lab2/task3/sigdelay.sv
module sigdelay #(
    parameter ADDRESS_WIDTH = 8,
              DATA_WIDTH = 8
)(
  // interface signals
  input  logic             clk,      // clock
  input  logic             rst,      // reset
  input  logic             wr,       // write
  input  logic             rd,       // read
  input  logic [ADDRESS_WIDTH-1:0] offset,
  input  logic [DATA_WIDTH-1:0] mic_signal,
  output logic [DATA_WIDTH-1:0] delayed_signal
);

logic [ADDRESS_WIDTH-1:0] address1;    // interconnect wire
logic [ADDRESS_WIDTH-1:0] address2;
assign address2 = address1 + offset;  

counter myCounter (
  .clk (clk),
  .rst (rst),
  .count (address1)
);

ram sineRAM (
  .clk (clk),
  .readEn (rd),
  .writeEn (wr),
  .writeAddr (address2),
  .readAddr (address1),
  .din (mic_signal),
  .dout (delayed_signal)
);

endmodule

lab2/task3/sigdelay.vcd
$version Generated by VerilatedVcd $end
$date Thu Oct 24 11:46:51 2024 $end
$timescale 1ps $end

 $scope module TOP $end
  $var wire  1 # clk $end
  $var wire  8 ) delayed_signal [7:0] $end
  $var wire  8 ( mic_signal [7:0] $end
  $var wire  8 ' offset [7:0] $end
  $var wire  1 & rd $end
  $var wire  1 $ rst $end
  $var wire  1 % wr $end
  $scope module sigdelay $end
   $var wire 32 . ADDRESS_WIDTH [31:0] $end
   $var wire 32 . DATA_WIDTH [31:0] $end
   $var wire  8 * address1 [7:0] $end
   $var wire  8 + address2 [7:0] $end
   $var wire  1 # clk $end
   $var wire  8 ) delayed_signal [7:0] $end
   $var wire  8 ( mic_signal [7:0] $end
   $var wire  8 ' offset [7:0] $end
   $var wire  1 & rd $end
   $var wire  1 $ rst $end
   $var wire  1 % wr $end
   $scope module myCounter $end
    $var wire 32 . WIDTH [31:0] $end
    $var wire  1 # clk $end
    $var wire  8 * count [7:0] $end
    $var wire  1 $ rst $end
   $upscope $end
   $scope module sineRAM $end
    $var wire 32 / ADDRESS_WIDTH [31:0] $end
    $var wire 32 . DATA_WIDTH [31:0] $end
    $var wire  1 # clk $end
    $var wire  8 ( din [7:0] $end
    $var wire  8 ) dout [7:0] $end
    $var wire  9 - readAddr [8:0] $end
    $var wire  1 & readEn $end
    $var wire  9 , writeAddr [8:0] $end
    $var wire  1 % writeEn $end
   $upscope $end
  $upscope $end
 $upscope $end
$enddefinitions $end


#0
1#
0$
1%
1&
b10000000 '
b00000000 (
b00000000 )
b00000000 *
b10000000 +
b010000000 ,
b000000000 -
b00000000000000000000000000001000 .
b00000000000000000000000000001001 /
#1
0#
#2
1#
b01000000 '
b01101111 (
b00000001 *
b01000001 +
b001000001 ,
b000000001 -
#3
0#
#4
1#
b01111000 (
b00000010 *
b01000010 +
b001000010 ,
b000000010 -
#5
0#
#6
1#
b10000100 (
b00000011 *
b01000011 +
b001000011 ,
b000000011 -
#7
0#
#8
1#
b10000001 (
b00000100 *
b01000100 +
b001000100 ,
b000000100 -
#9
0#
#10
1#
b01111011 (
b00000101 *
b01000101 +
b001000101 ,
b000000101 -
#11
0#
#12
1#
b01101001 (
b00000110 *
b01000110 +
b001000110 ,
b000000110 -
#13
0#
#14
1#
b01101011 (
b00000111 *
b01000111 +
b001000111 ,
b000000111 -
#15
0#
#16
1#
b01111011 (
b00001000 *
b01001000 +
b001001000 ,
b000001000 -
#17
0#
#18
1#
b01111100 (
b00001001 *
b01001001 +
b001001001 ,
b000001001 -
#19
0#
#20
1#
b01101111 (
b00001010 *
b01001010 +
b001001010 ,
b000001010 -
#21
0#
#22
1#
b01100011 (
b00001011 *
b01001011 +
b001001011 ,
b000001011 -
#23
0#
#24
1#
b01101111 (
b00001100 *
b01001100 +
b001001100 ,
b000001100 -
#25
0#
#26
1#
b01111000 (
b00001101 *
b01001101 +
b001001101 ,
b000001101 -
#27
0#
#28
1#
b01110111 (
b00001110 *
b01001110 +
b001001110 ,
b000001110 -
#29
0#
#30
1#
b01111001 (
b00001111 *
b01001111 +
b001001111 ,
b000001111 -
#31
0#
#32
1#
b01110111 (
b00010000 *
b01010000 +
b001010000 ,
b000010000 -
#33
0#
#34
1#
b10000001 (
b00010001 *
b01010001 +
b001010001 ,
b000010001 -
#35
0#
#36
1#
b10001011 (
b00010010 *
b01010010 +
b001010010 ,
b000010010 -
#37
0#
#38
1#
b10001000 (
b00010011 *
b01010011 +
b001010011 ,
b000010011 -
#39
0#
#40
1#
b10000011 (
b00010100 *
b01010100 +
b001010100 ,
b000010100 -
#41
0#
#42
1#
b01111001 (
b00010101 *
b01010101 +
b001010101 ,
b000010101 -
#43
0#
#44
1#
b01110010 (
b00010110 *
b01010110 +
b001010110 ,
b000010110 -
#45
0#
#46
1#
b01101100 (
b00010111 *
b01010111 +
b001010111 ,
b000010111 -
#47
0#
#48
1#
b01101010 (
b00011000 *
b01011000 +
b001011000 ,
b000011000 -
#49
0#
#50
1#
b01011000 (
b00011001 *
b01011001 +
b001011001 ,
b000011001 -
#51
0#
#52
1#
b01000011 (
b00011010 *
b01011010 +
b001011010 ,
b000011010 -
#53
0#
#54
1#
b01011000 (
b00011011 *
b01011011 +
b001011011 ,
b000011011 -
#55
0#
#56
1#
b01011110 (
b00011100 *
b01011100 +
b001011100 ,
b000011100 -
#57
0#
#58
1#
b01010101 (
b00011101 *
b01011101 +
b001011101 ,
b000011101 -
#59
0#
#60
1#
b01010001 (
b00011110 *
b01011110 +
b001011110 ,
b000011110 -
#61
0#
#62
1#
b01010110 (
b00011111 *
b01011111 +
b001011111 ,
b000011111 -
#63
0#
#64
1#
b01100010 (
b00100000 *
b01100000 +
b001100000 ,
b000100000 -
#65
0#
#66
1#
b01101101 (
b00100001 *
b01100001 +
b001100001 ,
b000100001 -
#67
0#
#68
1#
b01111001 (
b00100010 *
b01100010 +
b001100010 ,
b000100010 -
#69
0#
#70
1#
b01110111 (
b00100011 *
b01100011 +
b001100011 ,
b000100011 -
#71
0#
#72
1#
b01110100 (
b00100100 *
b01100100 +
b001100100 ,
b000100100 -
#73
0#
#74
1#
b01110101 (
b00100101 *
b01100101 +
b001100101 ,
b000100101 -
#75
0#
#76
1#
b01111101 (
b00100110 *
b01100110 +
b001100110 ,
b000100110 -
#77
0#
#78
1#
b10000010 (
b00100111 *
b01100111 +
b001100111 ,
b000100111 -
#79
0#
#80
1#
b01101101 (
b00101000 *
b01101000 +
b001101000 ,
b000101000 -
#81
0#
#82
1#
b01100000 (
b00101001 *
b01101001 +
b001101001 ,
b000101001 -
#83
0#
#84
1#
b01100011 (
b00101010 *
b01101010 +
b001101010 ,
b000101010 -
#85
0#
#86
1#
b01011010 (
b00101011 *
b01101011 +
b001101011 ,
b000101011 -
#87
0#
#88
1#
b01010001 (
b00101100 *
b01101100 +
b001101100 ,
b000101100 -
#89
0#
#90
1#
b01000111 (
b00101101 *
b01101101 +
b001101101 ,
b000101101 -
#91
0#
#92
1#
b01001001 (
b00101110 *
b01101110 +
b001101110 ,
b000101110 -
#93
0#
#94
1#
b01000100 (
b00101111 *
b01101111 +
b001101111 ,
b000101111 -
#95
0#
#96
1#
b00111101 (
b00110000 *
b01110000 +
b001110000 ,
b000110000 -
#97
0#
#98
1#
b01000110 (
b00110001 *
b01110001 +
b001110001 ,
b000110001 -
#99
0#
#100
1#
b01010000 (
b00110010 *
b01110010 +
b001110010 ,
b000110010 -
#101
0#
#102
1#
b01010100 (
b00110011 *
b01110011 +
b001110011 ,
b000110011 -
#103
0#
#104
1#
b01011111 (
b00110100 *
b01110100 +
b001110100 ,
b000110100 -
#105
0#
#106
1#
b01101100 (
b00110101 *
b01110101 +
b001110101 ,
b000110101 -
#107
0#
#108
1#
b01110011 (
b00110110 *
b01110110 +
b001110110 ,
b000110110 -
#109
0#
#110
1#
b01110001 (
b00110111 *
b01110111 +
b001110111 ,
b000110111 -
#111
0#
#112
1#
b01111000 (
b00111000 *
b01111000 +
b001111000 ,
b000111000 -
#113
0#
#114
1#
b01111011 (
b00111001 *
b01111001 +
b001111001 ,
b000111001 -
#115
0#
#116
1#
b01110111 (
b00111010 *
b01111010 +
b001111010 ,
b000111010 -
#117
0#
#118
1#
b01110101 (
b00111011 *
b01111011 +
b001111011 ,
b000111011 -
#119
0#
#120
1#
b01101110 (
b00111100 *
b01111100 +
b001111100 ,
b000111100 -
#121
0#
#122
1#
b01100010 (
b00111101 *
b01111101 +
b001111101 ,
b000111101 -
#123
0#
#124
1#
b01011100 (
b00111110 *
b01111110 +
b001111110 ,
b000111110 -
#125
0#
#126
1#
b00111111 *
b01111111 +
b001111111 ,
b000111111 -
#127
0#
#128
1#
b01010011 (
b01000000 *
b10000000 +
b010000000 ,
b001000000 -
#129
0#
#130
1#
b01001111 (
b01000001 *
b10000001 +
b010000001 ,
b001000001 -
#131
0#
#132
1#
b01010000 (
b01101111 )
b01000010 *
b10000010 +
b010000010 ,
b001000010 -
#133
0#
#134
1#
b01001110 (
b01111000 )
b01000011 *
b10000011 +
b010000011 ,
b001000011 -
#135
0#
#136
1#
b01001001 (
b10000100 )
b01000100 *
b10000100 +
b010000100 ,
b001000100 -
#137
0#
#138
1#
b01010001 (
b10000001 )
b01000101 *
b10000101 +
b010000101 ,
b001000101 -
#139
0#
#140
1#
b01011100 (
b01111011 )
b01000110 *
b10000110 +
b010000110 ,
b001000110 -
#141
0#
#142
1#
b01100111 (
b01101001 )
b01000111 *
b10000111 +
b010000111 ,
b001000111 -
#143
0#
#144
1#
b01100110 (
b01101011 )
b01001000 *
b10001000 +
b010001000 ,
b001001000 -
#145
0#
#146
1#
b01101111 (
b01111011 )
b01001001 *
b10001001 +
b010001001 ,
b001001001 -
#147
0#
#148
1#
b01101011 (
b01111100 )
b01001010 *
b10001010 +
b010001010 ,
b001001010 -
#149
0#
#150
1#
b01110001 (
b01101111 )
b01001011 *
b10001011 +
b010001011 ,
b001001011 -
#151
0#
#152
1#
b01111110 (
b01100011 )
b01001100 *
b10001100 +
b010001100 ,
b001001100 -
#153
0#
#154
1#
b01111011 (
b01101111 )
b01001101 *
b10001101 +
b010001101 ,
b001001101 -
#155
0#
#156
1#
b01101111 (
b01111000 )
b01001110 *
b10001110 +
b010001110 ,
b001001110 -
#157
0#
#158
1#
b01100011 (
b01110111 )
b01001111 *
b10001111 +
b010001111 ,
b001001111 -
#159
0#
#160
1#
b01101101 (
b01111001 )
b01010000 *
b10010000 +
b010010000 ,
b001010000 -
#161
0#
#162
1#
b01110001 (
b01110111 )
b01010001 *
b10010001 +
b010010001 ,
b001010001 -
#163
0#
#164
1#
b01100110 (
b10000001 )
b01010010 *
b10010010 +
b010010010 ,
b001010010 -
#165
0#
#166
1#
b01100101 (
b10001011 )
b01010011 *
b10010011 +
b010010011 ,
b001010011 -
#167
0#
#168
1#
b01100010 (
b10001000 )
b01010100 *
b10010100 +
b010010100 ,
b001010100 -
#169
0#
#170
1#
b01011111 (
b10000011 )
b01010101 *
b10010101 +
b010010101 ,
b001010101 -
#171
0#
#172
1#
b01101001 (
b01111001 )
b01010110 *
b10010110 +
b010010110 ,
b001010110 -
#173
0#
#174
1#
b01110001 (
b01110010 )
b01010111 *
b10010111 +
b010010111 ,
b001010111 -
#175
0#
#176
1#
b01110010 (
b01101100 )
b01011000 *
b10011000 +
b010011000 ,
b001011000 -
#177
0#
#178
1#
b01101011 (
b01101010 )
b01011001 *
b10011001 +
b010011001 ,
b001011001 -
#179
0#
#180
1#
b01110100 (
b01011000 )
b01011010 *
b10011010 +
b010011010 ,
b001011010 -
#181
0#
#182
1#
b01111111 (
b01000011 )
b01011011 *
b10011011 +
b010011011 ,
b001011011 -
#183
0#
#184
1#
b01110100 (
b01011000 )
b01011100 *
b10011100 +
b010011100 ,
b001011100 -
#185
0#
#186
1#
b01111111 (
b01011110 )
b01011101 *
b10011101 +
b010011101 ,
b001011101 -
#187
0#
#188
1#
b10000101 (
b01010101 )
b01011110 *
b10011110 +
b010011110 ,
b001011110 -
#189
0#
#190
1#
b01111100 (
b01010001 )
b01011111 *
b10011111 +
b010011111 ,
b001011111 -
#191
0#
#192
1#
b01110001 (
b01010110 )
b01100000 *
b10100000 +
b010100000 ,
b001100000 -
#193
0#
#194
1#
b01110111 (
b01100010 )
b01100001 *
b10100001 +
b010100001 ,
b001100001 -
#195
0#
#196
1#
b01110100 (
b01101101 )
b01100010 *
b10100010 +
b010100010 ,
b001100010 -
#197
0#
#198
1#
b01011101 (
b01111001 )
b01100011 *
b10100011 +
b010100011 ,
b001100011 -
#199
0#
#200
1#
b01011000 (
b01110111 )
b01100100 *
b10100100 +
b010100100 ,
b001100100 -
#201
0#
#202
1#
b01011110 (
b01110100 )
b01100101 *
b10100101 +
b010100101 ,
b001100101 -
#203
0#
#204
1#
b01010110 (
b01110101 )
b01100110 *
b10100110 +
b010100110 ,
b001100110 -
#205
0#
#206
1#
b01010100 (
b01111101 )
b01100111 *
b10100111 +
b010100111 ,
b001100111 -
#207
0#
#208
1#
b01010001 (
b10000010 )
b01101000 *
b10101000 +
b010101000 ,
b001101000 -
#209
0#
#210
1#
b01011011 (
b01101101 )
b01101001 *
b10101001 +
b010101001 ,
b001101001 -
#211
0#
#212
1#
b01010101 (
b01100000 )
b01101010 *
b10101010 +
b010101010 ,
b001101010 -
#213
0#
#214
1#
b01001110 (
b01100011 )
b01101011 *
b10101011 +
b010101011 ,
b001101011 -
#215
0#
#216
1#
b01100001 (
b01011010 )
b01101100 *
b10101100 +
b010101100 ,
b001101100 -
#217
0#
#218
1#
b01101001 (
b01010001 )
b01101101 *
b10101101 +
b010101101 ,
b001101101 -
#219
0#
#220
1#
b01100111 (
b01000111 )
b01101110 *
b10101110 +
b010101110 ,
b001101110 -
#221
0#
#222
1#
b01101010 (
b01001001 )
b01101111 *
b10101111 +
b010101111 ,
b001101111 -
#223
0#
#224
1#
b01110101 (
b01000100 )
b01110000 *
b10110000 +
b010110000 ,
b001110000 -
#225
0#
#226
1#
b00111101 )
b01110001 *
b10110001 +
b010110001 ,
b001110001 -
#227
0#
#228
1#
b01101000 (
b01000110 )
b01110010 *
b10110010 +
b010110010 ,
b001110010 -
#229
0#
#230
1#
b01110001 (
b01010000 )
b01110011 *
b10110011 +
b010110011 ,
b001110011 -
#231
0#
#232
1#
b01111001 (
b01010100 )
b01110100 *
b10110100 +
b010110100 ,
b001110100 -
#233
0#
#234
1#
b01100101 (
b01011111 )
b01110101 *
b10110101 +
b010110101 ,
b001110101 -
#235
0#
#236
1#
b01010110 (
b01101100 )
b01110110 *
b10110110 +
b010110110 ,
b001110110 -
#237
0#
#238
1#
b01011100 (
b01110011 )
b01110111 *
b10110111 +
b010110111 ,
b001110111 -
#239
0#
#240
1#
b01101010 (
b01110001 )
b01111000 *
b10111000 +
b010111000 ,
b001111000 -
#241
0#
#242
1#
b01100000 (
b01111000 )
b01111001 *
b10111001 +
b010111001 ,
b001111001 -
#243
0#
#244
1#
b01010000 (
b01111011 )
b01111010 *
b10111010 +
b010111010 ,
b001111010 -
#245
0#
#246
1#
b01010111 (
b01110111 )
b01111011 *
b10111011 +
b010111011 ,
b001111011 -
#247
0#
#248
1#
b01001110 (
b01110101 )
b01111100 *
b10111100 +
b010111100 ,
b001111100 -
#249
0#
#250
1#
b01010111 (
b01101110 )
b01111101 *
b10111101 +
b010111101 ,
b001111101 -
#251
0#
#252
1#
b01100000 (
b01100010 )
b01111110 *
b10111110 +
b010111110 ,
b001111110 -
#253
0#
#254
1#
b01100010 (
b01011100 )
b01111111 *
b10111111 +
b010111111 ,
b001111111 -
#255
0#
#256
1#
b01011011 (
b10000000 *
b11000000 +
b011000000 ,
b010000000 -
#257
0#
#258
1#
b01001110 (
b01010011 )
b10000001 *
b11000001 +
b011000001 ,
b010000001 -
#259
0#
#260
1#
b01011101 (
b01001111 )
b10000010 *
b11000010 +
b011000010 ,
b010000010 -
#261
0#
#262
1#
b01011001 (
b01010000 )
b10000011 *
b11000011 +
b011000011 ,
b010000011 -
#263
0#
#264
1#
b01001001 (
b01001110 )
b10000100 *
b11000100 +
b011000100 ,
b010000100 -
#265
0#
#266
1#
b01011001 (
b01001001 )
b10000101 *
b11000101 +
b011000101 ,
b010000101 -
#267
0#
#268
1#
b01011101 (
b01010001 )
b10000110 *
b11000110 +
b011000110 ,
b010000110 -
#269
0#
#270
1#
b01011000 (
b01011100 )
b10000111 *
b11000111 +
b011000111 ,
b010000111 -
#271
0#
#272
1#
b01100001 (
b01100111 )
b10001000 *
b11001000 +
b011001000 ,
b010001000 -
#273
0#
#274
1#
b01101011 (
b01100110 )
b10001001 *
b11001001 +
b011001001 ,
b010001001 -
#275
0#
#276
1#
b01101001 (
b01101111 )
b10001010 *
b11001010 +
b011001010 ,
b010001010 -
#277
0#
#278
1#
b01100100 (
b01101011 )
b10001011 *
b11001011 +
b011001011 ,
b010001011 -
#279
0#
#280
1#
b01101010 (
b01110001 )
b10001100 *
b11001100 +
b011001100 ,
b010001100 -
#281
0#
#282
1#
b01101000 (
b01111110 )
b10001101 *
b11001101 +
b011001101 ,
b010001101 -
#283
0#
#284
1#
b01101001 (
b01111011 )
b10001110 *
b11001110 +
b011001110 ,
b010001110 -
#285
0#
#286
1#
b01101111 (
b01101111 )
b10001111 *
b11001111 +
b011001111 ,
b010001111 -
#287
0#
#288
1#
b01101000 (
b01100011 )
b10010000 *
b11010000 +
b011010000 ,
b010010000 -
#289
0#
#290
1#
b01100101 (
b01101101 )
b10010001 *
b11010001 +
b011010001 ,
b010010001 -
#291
0#
#292
1#
b01011111 (
b01110001 )
b10010010 *
b11010010 +
b011010010 ,
b010010010 -
#293
0#
#294
1#
b01101000 (
b01100110 )
b10010011 *
b11010011 +
b011010011 ,
b010010011 -
#295
0#
#296
1#
b01100010 (
b01100101 )
b10010100 *
b11010100 +
b011010100 ,
b010010100 -
#297
0#
#298
1#
b01010011 (
b01100010 )
b10010101 *
b11010101 +
b011010101 ,
b010010101 -
#299
0#
#300
1#
b01010111 (
b01011111 )
b10010110 *
b11010110 +
b011010110 ,
b010010110 -
#301
0#
#302
1#
b01100101 (
b01101001 )
b10010111 *
b11010111 +
b011010111 ,
b010010111 -
#303
0#
#304
1#
b01101000 (
b01110001 )
b10011000 *
b11011000 +
b011011000 ,
b010011000 -
#305
0#
#306
1#
b01100001 (
b01110010 )
b10011001 *
b11011001 +
b011011001 ,
b010011001 -
#307
0#
#308
1#
b01010101 (
b01101011 )
b10011010 *
b11011010 +
b011011010 ,
b010011010 -
#309
0#
#310
1#
b01011100 (
b01110100 )
b10011011 *
b11011011 +
b011011011 ,
b010011011 -
#311
0#
#312
1#
b01100011 (
b01111111 )
b10011100 *
b11011100 +
b011011100 ,
b010011100 -
#313
0#
#314
1#
b01101010 (
b01110100 )
b10011101 *
b11011101 +
b011011101 ,
b010011101 -
#315
0#
#316
1#
b01101011 (
b01111111 )
b10011110 *
b11011110 +
b011011110 ,
b010011110 -
#317
0#
#318
1#
b01101010 (
b10000101 )
b10011111 *
b11011111 +
b011011111 ,
b010011111 -
#319
0#
#320
1#
b01110101 (
b01111100 )
b10100000 *
b11100000 +
b011100000 ,
b010100000 -
#321
0#
#322
1#
b01110100 (
b01110001 )
b10100001 *
b11100001 +
b011100001 ,
b010100001 -
#323
0#
#324
1#
b01110111 )
b10100010 *
b11100010 +
b011100010 ,
b010100010 -
#325
0#
#326
1#
b01111011 (
b01110100 )
b10100011 *
b11100011 +
b011100011 ,
b010100011 -
#327
0#
#328
1#
b01110110 (
b01011101 )
b10100100 *
b11100100 +
b011100100 ,
b010100100 -
#329
0#
#330
1#
b01110100 (
b01011000 )
b10100101 *
b11100101 +
b011100101 ,
b010100101 -
#331
0#
#332
1#
b01110011 (
b01011110 )
b10100110 *
b11100110 +
b011100110 ,
b010100110 -
#333
0#
#334
1#
b01111110 (
b01010110 )
b10100111 *
b11100111 +
b011100111 ,
b010100111 -
#335
0#
#336
1#
b10000001 (
b01010100 )
b10101000 *
b11101000 +
b011101000 ,
b010101000 -
#337
0#
#338
1#
b01111101 (
b01010001 )
b10101001 *
b11101001 +
b011101001 ,
b010101001 -
#339
0#
#340
1#
b01110110 (
b01011011 )
b10101010 *
b11101010 +
b011101010 ,
b010101010 -
#341
0#
#342
1#
b01101011 (
b01010101 )
b10101011 *
b11101011 +
b011101011 ,
b010101011 -
#343
0#
#344
1#
b01111000 (
b01001110 )
b10101100 *
b11101100 +
b011101100 ,
b010101100 -
#345
0#
#346
1#
b10000001 (
b01100001 )
b10101101 *
b11101101 +
b011101101 ,
b010101101 -
#347
0#
#348
1#
b01111111 (
b01101001 )
b10101110 *
b11101110 +
b011101110 ,
b010101110 -
#349
0#
#350
1#
b01110010 (
b01100111 )
b10101111 *
b11101111 +
b011101111 ,
b010101111 -
#351
0#
#352
1#
b01101010 (
b01101010 )
b10110000 *
b11110000 +
b011110000 ,
b010110000 -
#353
0#
#354
1#
b01110110 (
b01110101 )
b10110001 *
b11110001 +
b011110001 ,
b010110001 -
#355
0#
#356
1#
b01111001 (
b10110010 *
b11110010 +
b011110010 ,
b010110010 -
#357
0#
#358
1#
b01101010 (
b01101000 )
b10110011 *
b11110011 +
b011110011 ,
b010110011 -
#359
0#
#360
1#
b01011001 (
b01110001 )
b10110100 *
b11110100 +
b011110100 ,
b010110100 -
#361
0#
#362
1#
b01010110 (
b01111001 )
b10110101 *
b11110101 +
b011110101 ,
b010110101 -
#363
0#
#364
1#
b01101011 (
b01100101 )
b10110110 *
b11110110 +
b011110110 ,
b010110110 -
#365
0#
#366
1#
b01101001 (
b01010110 )
b10110111 *
b11110111 +
b011110111 ,
b010110111 -
#367
0#
#368
1#
b01100010 (
b01011100 )
b10111000 *
b11111000 +
b011111000 ,
b010111000 -
#369
0#
#370
1#
b01011001 (
b01101010 )
b10111001 *
b11111001 +
b011111001 ,
b010111001 -
#371
0#
#372
1#
b01010100 (
b01100000 )
b10111010 *
b11111010 +
b011111010 ,
b010111010 -
#373
0#
#374
1#
b01100000 (
b01010000 )
b10111011 *
b11111011 +
b011111011 ,
b010111011 -
#375
0#
#376
1#
b01100101 (
b01010111 )
b10111100 *
b11111100 +
b011111100 ,
b010111100 -
#377
0#
#378
1#
b01001110 )
b10111101 *
b11111101 +
b011111101 ,
b010111101 -
#379
0#
#380
1#
b01100001 (
b01010111 )
b10111110 *
b11111110 +
b011111110 ,
b010111110 -
#381
0#
#382
1#
b01001101 (
b01100000 )
b10111111 *
b11111111 +
b011111111 ,
b010111111 -
#383
0#
#384
1#
b01100100 (
b01100010 )
b11000000 *
b00000000 +
b000000000 ,
b011000000 -
#385
0#
#386
1#
b01101010 (
b01011011 )
b11000001 *
b00000001 +
b000000001 ,
b011000001 -
#387
0#
#388
1#
b01100001 (
b01001110 )
b11000010 *
b00000010 +
b000000010 ,
b011000010 -
#389
0#
#390
1#
b01010100 (
b01011101 )
b11000011 *
b00000011 +
b000000011 ,
b011000011 -
#391
0#
#392
1#
b01011001 )
b11000100 *
b00000100 +
b000000100 ,
b011000100 -
#393
0#
#394
1#
b01100110 (
b01001001 )
b11000101 *
b00000101 +
b000000101 ,
b011000101 -
#395
0#
#396
1#
b01101101 (
b01011001 )
b11000110 *
b00000110 +
b000000110 ,
b011000110 -
#397
0#
#398
1#
b01101100 (
b01011101 )
b11000111 *
b00000111 +
b000000111 ,
b011000111 -
#399
0#
#400
1#
b01101000 (
b01011000 )
b11001000 *
b00001000 +
b000001000 ,
b011001000 -
#401
0#
#402
1#
b01011111 (
b01100001 )
b11001001 *
b00001001 +
b000001001 ,
b011001001 -
#403
0#
#404
1#
b01100011 (
b01101011 )
b11001010 *
b00001010 +
b000001010 ,
b011001010 -
#405
0#
#406
1#
b01100001 (
b01101001 )
b11001011 *
b00001011 +
b000001011 ,
b011001011 -
#407
0#
#408
1#
b01100101 (
b01100100 )
b11001100 *
b00001100 +
b000001100 ,
b011001100 -
#409
0#
#410
1#
b01011101 (
b01101010 )
b11001101 *
b00001101 +
b000001101 ,
b011001101 -
#411
0#
#412
1#
b01010101 (
b01101000 )
b11001110 *
b00001110 +
b000001110 ,
b011001110 -
#413
0#
#414
1#
b01011110 (
b01101001 )
b11001111 *
b00001111 +
b000001111 ,
b011001111 -
#415
0#
#416
1#
b01101001 (
b01101111 )
b11010000 *
b00010000 +
b000010000 ,
b011010000 -
#417
0#
#418
1#
b01101010 (
b01101000 )
b11010001 *
b00010001 +
b000010001 ,
b011010001 -
#419
0#
#420
1#
b01100010 (
b01100101 )
b11010010 *
b00010010 +
b000010010 ,
b011010010 -
#421
0#
#422
1#
b01011001 (
b01011111 )
b11010011 *
b00010011 +
b000010011 ,
b011010011 -
#423
0#
#424
1#
b01100000 (
b01101000 )
b11010100 *
b00010100 +
b000010100 ,
b011010100 -
#425
0#
#426
1#
b01100101 (
b01100010 )
b11010101 *
b00010101 +
b000010101 ,
b011010101 -
#427
0#
#428
1#
b01100100 (
b01010011 )
b11010110 *
b00010110 +
b000010110 ,
b011010110 -
#429
0#
#430
1#
b01010111 )
b11010111 *
b00010111 +
b000010111 ,
b011010111 -
#431
0#
#432
1#
b01100101 )
b11011000 *
b00011000 +
b000011000 ,
b011011000 -
#433
0#
#434
1#
b01100001 (
b01101000 )
b11011001 *
b00011001 +
b000011001 ,
b011011001 -
#435
0#
#436
1#
b01011100 (
b01100001 )
b11011010 *
b00011010 +
b000011010 ,
b011011010 -
#437
0#
#438
1#
b01010111 (
b01010101 )
b11011011 *
b00011011 +
b000011011 ,
b011011011 -
#439
0#
#440
1#
b01011100 )
b11011100 *
b00011100 +
b000011100 ,
b011011100 -
#441
0#
#442
1#
b01011110 (
b01100011 )
b11011101 *
b00011101 +
b000011101 ,
b011011101 -
#443
0#
#444
1#
b01100011 (
b01101010 )
b11011110 *
b00011110 +
b000011110 ,
b011011110 -
#445
0#
#446
1#
b01101000 (
b01101011 )
b11011111 *
b00011111 +
b000011111 ,
b011011111 -
#447
0#
#448
1#
b01101001 (
b01101010 )
b11100000 *
b00100000 +
b000100000 ,
b011100000 -
#449
0#
#450
1#
b01100011 (
b01110101 )
b11100001 *
b00100001 +
b000100001 ,
b011100001 -
#451
0#
#452
1#
b01110011 (
b01110100 )
b11100010 *
b00100010 +
b000100010 ,
b011100010 -
#453
0#
#454
1#
b10000000 (
b11100011 *
b00100011 +
b000100011 ,
b011100011 -
#455
0#
#456
1#
b01111101 (
b01111011 )
b11100100 *
b00100100 +
b000100100 ,
b011100100 -
#457
0#
#458
1#
b01110111 (
b01110110 )
b11100101 *
b00100101 +
b000100101 ,
b011100101 -
#459
0#
#460
1#
b01111000 (
b01110100 )
b11100110 *
b00100110 +
b000100110 ,
b011100110 -
#461
0#
#462
1#
b01111111 (
b01110011 )
b11100111 *
b00100111 +
b000100111 ,
b011100111 -
#463
0#
#464
1#
b10000110 (
b01111110 )
b11101000 *
b00101000 +
b000101000 ,
b011101000 -
#465
0#
#466
1#
b01111010 (
b10000001 )
b11101001 *
b00101001 +
b000101001 ,
b011101001 -
#467
0#
#468
1#
b01101010 (
b01111101 )
b11101010 *
b00101010 +
b000101010 ,
b011101010 -
#469
0#
#470
1#
b01100100 (
b01110110 )
b11101011 *
b00101011 +
b000101011 ,
b011101011 -
#471
0#
#472
1#
b01101001 (
b01101011 )
b11101100 *
b00101100 +
b000101100 ,
b011101100 -
#473
0#
#474
1#
b01101101 (
b01111000 )
b11101101 *
b00101101 +
b000101101 ,
b011101101 -
#475
0#
#476
1#
b01101001 (
b10000001 )
b11101110 *
b00101110 +
b000101110 ,
b011101110 -
#477
0#
#478
1#
b01011111 (
b01111111 )
b11101111 *
b00101111 +
b000101111 ,
b011101111 -
#479
0#
#480
1#
b01011000 (
b01110010 )
b11110000 *
b00110000 +
b000110000 ,
b011110000 -
#481
0#
#482
1#
b01011111 (
b01101010 )
b11110001 *
b00110001 +
b000110001 ,
b011110001 -
#483
0#
#484
1#
b01100011 (
b01110110 )
b11110010 *
b00110010 +
b000110010 ,
b011110010 -
#485
0#
#486
1#
b01100110 (
b01111001 )
b11110011 *
b00110011 +
b000110011 ,
b011110011 -
#487
0#
#488
1#
b01100111 (
b01101010 )
b11110100 *
b00110100 +
b000110100 ,
b011110100 -
#489
0#
#490
1#
b01101010 (
b01011001 )
b11110101 *
b00110101 +
b000110101 ,
b011110101 -
#491
0#
#492
1#
b01101101 (
b01010110 )
b11110110 *
b00110110 +
b000110110 ,
b011110110 -
#493
0#
#494
1#
b01111001 (
b01101011 )
b11110111 *
b00110111 +
b000110111 ,
b011110111 -
#495
0#
#496
1#
b01111110 (
b01101001 )
b11111000 *
b00111000 +
b000111000 ,
b011111000 -
#497
0#
#498
1#
b01110111 (
b01100010 )
b11111001 *
b00111001 +
b000111001 ,
b011111001 -
#499
0#
#500
1#
b01110010 (
b01011001 )
b11111010 *
b00111010 +
b000111010 ,
b011111010 -
#501
0#
#502
1#
b01110011 (
b01010100 )
b11111011 *
b00111011 +
b000111011 ,
b011111011 -
